plonegovbr/intranet/__init__.py
plonegovbr/intranet/about.py
plonegovbr/intranet/configure.zcml
plonegovbr/intranet/dependencies.zcml
plonegovbr/intranet/distributions.zcml
plonegovbr/intranet/handlers.py
plonegovbr/intranet/interfaces.py
plonegovbr/intranet/permissions.zcml
plonegovbr/intranet/profiles.zcml
plonegovbr/intranet/testing.py
plonegovbr/intranet/behaviors/__init__.py
plonegovbr/intranet/behaviors/configure.zcml
plonegovbr/intranet/behaviors/contato.py
plonegovbr/intranet/behaviors/endereco.py
plonegovbr/intranet/behaviors/matricula.py
plonegovbr/intranet/content/__init__.py
plonegovbr/intranet/content/area.py
plonegovbr/intranet/content/colaborador.py
plonegovbr/intranet/content/servico.py
plonegovbr/intranet/controlpanel/__init__.py
plonegovbr/intranet/controlpanel/configure.zcml
plonegovbr/intranet/distributions/intranet/image.png
plonegovbr/intranet/distributions/intranet/profiles.json
plonegovbr/intranet/distributions/intranet/schema.json
plonegovbr/intranet/distributions/intranet/content/discussions.json
plonegovbr/intranet/distributions/intranet/content/portlets.json
plonegovbr/intranet/distributions/intranet/content/principals.json
plonegovbr/intranet/distributions/intranet/content/redirects.json
plonegovbr/intranet/distributions/intranet/content/relations.json
plonegovbr/intranet/distributions/intranet/content/translations.json
plonegovbr/intranet/distributions/intranet/content/content/__metadata__.json
plonegovbr/intranet/distributions/intranet/content/content/0f37fe34245f439ba78901e36f6da9dc/data.json
plonegovbr/intranet/distributions/intranet/content/content/26e5fc286fce4c2e9613411cc0f0663f/data.json
plonegovbr/intranet/distributions/intranet/content/content/42bb0222abfe4356949de633f5cc25e6/data.json
plonegovbr/intranet/distributions/intranet/content/content/87b599b4dd5a419da58c59632bace85c/data.json
plonegovbr/intranet/distributions/intranet/content/content/abcd08c1843b4540b90cb73b9e9fc050/data.json
plonegovbr.intranet-1.0.0a4.dist-info/METADATA
plonegovbr.intranet-1.0.0a4.dist-info/WHEEL
plonegovbr.intranet-1.0.0a4.dist-info/entry_points.txt
plonegovbr.intranet-1.0.0a4.dist-info/licenses/LICENSE.GPL
plonegovbr.intranet-1.0.0a4.dist-info/licenses/LICENSE.md
plonegovbr.intranet-1.0.0a4.dist-info/RECORD
