Metadata-Version: 2.3
Name: plonegovbr.intranet
Version: 1.0.0a4
Summary: Solução de Intranet construída com Plone
Project-URL: Documentation, https://github.com/plonegovbr/portalbrasil-intranet#readme
Project-URL: Issues, https://github.com/plonegovbr/portalbrasil-intranet/issues
Project-URL: Source, https://github.com/plonegovbr/portalbrasil-intranet
Author-email: PloneGov-BR <gov@plone.org.br>
License-Expression: MIT
License-File: LICENSE.GPL
License-File: LICENSE.md
Keywords: Brasil,Intranet,Plone,Python
Classifier: Development Status :: 3 - Alpha
Classifier: Environment :: Web Environment
Classifier: Framework :: Plone
Classifier: Framework :: Plone :: 6.0
Classifier: Framework :: Plone :: Distribution
Classifier: License :: OSI Approved :: GNU General Public License v2 (GPLv2)
Classifier: Operating System :: OS Independent
Classifier: Programming Language :: Python
Classifier: Programming Language :: Python :: 3.8
Classifier: Programming Language :: Python :: 3.9
Classifier: Programming Language :: Python :: 3.10
Classifier: Programming Language :: Python :: 3.11
Classifier: Programming Language :: Python :: 3.12
Requires-Python: >=3.8
Requires-Dist: collective-bookmarks
Requires-Dist: collective-honeypot
Requires-Dist: collective-taxonomy
Requires-Dist: collective-volto-formsupport>=3.1.4
Requires-Dist: collective-volto-otp
Requires-Dist: plone-api
Requires-Dist: plone-app-upgrade
Requires-Dist: plone-distribution>=2.0.0a1
Requires-Dist: plone-exportimport>=1.0.0a8
Requires-Dist: plone-restapi
Requires-Dist: plone-volto
